{"is_source_file": false, "format": "", "description": "", "external_files": [], "external_methods": [], "published": [], "classes": [], "methods": [], "calls": [], "search-terms": [], "state": 2, "file_id": 3, "knowledge_revision": 17, "git_revision": "6cd79149c72fb7ce0ca0c489b6d1b692cbf657d6", "hash": "d836a3d2dc8d37a6b1813c272899678c", "format-version": 4, "code-base-name": "notes_frontend", "filename": "notes_frontend/package.json", "revision_history": [{"17": "6cd79149c72fb7ce0ca0c489b6d1b692cbf657d6"}]}